{
  "total_trends": 106,
  "total_sources": 63,
  "by_category": {
    "Tile Design & Trends": 20,
    "Bath Fittings": 4,
    "Elevation Tiles": 1,
    "Eco-Friendly & Sustainability": 1,
    "Technology & Innovation": 2,
    "Special Tiles": 1,
    "Market & Industry News": 25,
    "Ceramic Tiles": 7,
    "General Trend": 17,
    "Sanitaryware": 3,
    "Terrazzo": 1,
    "Floor Tiles": 11,
    "New Collection Launch": 8,
    "Terrace & Outdoor Tiles": 1,
    "Large Format Tiles": 1,
    "Kitchen Tiles": 2,
    "Exhibition & Events": 1
  },
  "by_region": {
    "India": 46,
    "Global": 60
  },
  "by_source": {
    "Orient Bell": 1,
    "Cera Sanitaryware": 1,
    "ArchDaily Tiles": 4,
    "AD HOC NEWS": 4,
    "Markets Mojo": 6,
    "openPR.com": 3,
    "Whalesbook": 6,
    "Trade Brains": 1,
    "Business Upturn": 1,
    "Business Standard": 1,
    "scanx.trade": 4,
    "Free Press Journal": 2,
    "Prop News Time": 1,
    "Dailyhunt": 1,
    "Architectural Digest India": 1,
    "Adgully.com": 1,
    "IndexBox": 3,
    "gasworld": 1,
    "simplywall.st": 1,
    "Greater Kashmir": 1,
    "thehawk.in": 1,
    "DeshGujarat": 1,
    "Punjab Kesari English": 1,
    "pim-international.com": 1,
    "Outlook Luxe": 1,
    "AOL.com": 4,
    "Architectural Digest": 2,
    "MSN": 4,
    "Floor Covering News": 4,
    "GuruFocus": 1,
    "Proactive financial news": 1,
    "Hawaii Business Magazine": 1,
    "StockStory": 1,
    "Investing.com": 1,
    "newagebd.net": 1,
    "9and10News.com": 1,
    "Morocco World News": 1,
    "Floor Covering Weekly": 5,
    "ELLE Decor": 1,
    "Yahoo": 4,
    "Statesboro Herald": 1,
    "The Times of India": 1,
    "Qualified Remodeler": 1,
    "New York Post": 1,
    "Patch": 1,
    "kliksolonews.com": 1,
    "Inside Local Government": 1,
    "Cache Valley Daily": 1,
    "The Spruce": 1,
    "K-ARTNOW": 1,
    "WGCU": 1,
    "Dezeen": 1,
    "Bergen Record": 1,
    "Designboom": 1,
    "PR Newswire": 1,
    "THP News": 1,
    "Hotel Designs": 1,
    "SunLive": 1,
    "freeyork": 1,
    "Newsband": 1,
    "Dezeen Tiles RSS": 2,
    "GNews Morbi Tiles": 1,
    "GNews Large Format": 2
  },
  "by_priority": {
    "medium": 74,
    "low": 22,
    "high": 10
  },
  "by_sentiment": {
    "positive": 54,
    "neutral": 48,
    "negative": 4
  },
  "trending_up": [
    "Tile Design & Trends",
    "Bath Fittings",
    "Market & Industry News",
    "Ceramic Tiles",
    "General Trend",
    "Sanitaryware",
    "Floor Tiles",
    "New Collection Launch"
  ]
}